LICENCE
MANIFEST.in
README.md
setup.py
paymill/__init__.py
paymill/paymill_context.py
paymill/models/__init__.py
paymill/models/address.py
paymill/models/checksum.py
paymill/models/client.py
paymill/models/fee.py
paymill/models/filter.py
paymill/models/invoice.py
paymill/models/offer.py
paymill/models/order.py
paymill/models/payment.py
paymill/models/paymill_list.py
paymill/models/preauthorization.py
paymill/models/refund.py
paymill/models/shopping_cart.py
paymill/models/shopping_cart_item.py
paymill/models/subscription.py
paymill/models/transaction.py
paymill/models/webhook.py
paymill/services/__init__.py
paymill/services/checksum_service.py
paymill/services/client_service.py
paymill/services/offer_service.py
paymill/services/payment_service.py
paymill/services/paymill_service.py
paymill/services/preauthorization_service.py
paymill/services/refund_service.py
paymill/services/subscription_service.py
paymill/services/transaction_service.py
paymill/services/webhook_service.py
paymill/utils/__init__.py
paymill/utils/abstract_http_client.py
paymill/utils/http_client.py
paymill/utils/pm_error.py
paymill_wrapper.egg-info/PKG-INFO
paymill_wrapper.egg-info/SOURCES.txt
paymill_wrapper.egg-info/dependency_links.txt
paymill_wrapper.egg-info/requires.txt
paymill_wrapper.egg-info/top_level.txt