Metadata-Version: 1.1
Name: paymill-wrapper
Version: 2.3.0
Summary: Python wrapper for PAYMILL API
Home-page: https://github.com/paymill/paymill-python
Author: Aleksandar Yalnazov
Author-email: aleksandar.yalnazov@qaiware.com
License: MIT
Platform: UNKNOWN
Classifier: Development Status :: 4 - Beta
Classifier: Environment :: Web Environment
Classifier: Intended Audience :: Developers
Classifier: Operating System :: OS Independent
Classifier: Programming Language :: Python
Classifier: Programming Language :: Python :: 3
Classifier: License :: OSI Approved :: MIT License
Classifier: Topic :: Internet :: WWW/HTTP
Classifier: Topic :: Software Development :: Libraries :: Python Modules
